sanskritayam/__init__.py
sanskritayam/__main__.py
sanskritayam/sanskritayam.py
sanskritayam-0.0.25.dist-info/METADATA
sanskritayam-0.0.25.dist-info/WHEEL
sanskritayam-0.0.25.dist-info/entry_points.txt
sanskritayam-0.0.25.dist-info/top_level.txt
sanskritayam-0.0.25.dist-info/RECORD
